reddwarf/__init__.py
reddwarf/data_exporter.py
reddwarf/data_loader.py
reddwarf/data_presenter.py
reddwarf/exceptions.py
reddwarf/helpers.py
reddwarf/models.py
reddwarf/implementations/__init__.py
reddwarf/implementations/base.py
reddwarf/implementations/polis.py
reddwarf/sklearn/__init__.py
reddwarf/sklearn/cluster.py
reddwarf/sklearn/model_selection.py
reddwarf/sklearn/pipeline.py
reddwarf/sklearn/transformers.py
reddwarf/types/__init__.py
reddwarf/types/polis.py
reddwarf/utils/__init__.py
reddwarf/utils/consensus.py
reddwarf/utils/matrix.py
reddwarf/utils/polismath.py
reddwarf/utils/statements.py
reddwarf/utils/stats.py
reddwarf/utils/clusterer/__init__.py
reddwarf/utils/clusterer/base.py
reddwarf/utils/clusterer/kmeans.py
reddwarf/utils/reducer/__init__.py
reddwarf/utils/reducer/base.py
reddwarf/utils/reducer/pca.py
red_dwarf-0.4.0.dist-info/METADATA
red_dwarf-0.4.0.dist-info/WHEEL
red_dwarf-0.4.0.dist-info/top_level.txt
red_dwarf-0.4.0.dist-info/RECORD
