Metadata-Version: 2.4
Name: red-dwarf
Version: 0.4.0
Summary: A DIMensional REDuction library for reproducing and experimenting with Polis-like data pipelines.
Requires-Python: >=3.10
Requires-Dist: pandas>=1.5.0
Requires-Dist: scikit-learn>=1.1.0
Requires-Dist: pydantic>=1.10.0
Requires-Dist: requests>=2.28.0
Requires-Dist: requests-cache
Requires-Dist: requests-ratelimiter>=0.4.0
Requires-Dist: fake-useragent>=1.4.0
Provides-Extra: alt-algos
Requires-Dist: pacmap>=0.7.0; extra == "alt-algos"
Requires-Dist: numba<0.63.0; (platform_machine == "x86_64" and sys_platform == "darwin" and python_version < "3.14") and extra == "alt-algos"
Requires-Dist: hdbscan>=0.8.41; extra == "alt-algos"
Provides-Extra: plots
Requires-Dist: concave-hull>=0.0.9; extra == "plots"
Requires-Dist: seaborn>=0.11.0; extra == "plots"
Requires-Dist: matplotlib>=3.5.0; extra == "plots"
Provides-Extra: all
Requires-Dist: red-dwarf[alt-algos,plots]; extra == "all"
Provides-Extra: dev
Requires-Dist: coverage>=6.0; extra == "dev"
Requires-Dist: ipywidgets>=8.0.0; extra == "dev"
Requires-Dist: mkdocs-same-dir>=0.1.3; extra == "dev"
Requires-Dist: mkdocstrings-python>=1.8.0; extra == "dev"
Requires-Dist: nbmake>=1.5.0; extra == "dev"
Requires-Dist: pytest-cov>=4.0.0; extra == "dev"
Requires-Dist: pytest>=7.0.0; extra == "dev"
